[
    {
        "_id": 1,
        "link": "https://cdn-factory.marketjs.com/en/uber-playable-ad/index.html",
        "img": "assets/img/games/game1.png",
        "video": "assets/video/games/game1.mp4",
        "is_recommended": false,
        "is_info": true
    },
    {
        "_id": 2,
        "link": "https://cdn-factory.marketjs.com/en/uber-playable-ad/index.html",
        "img": "assets/img/games/game2.png",
        "video": "assets/video/games/game2.mp4",
        "is_recommended": true,
        "is_info": false
    },
    {
        "_id": 3,
        "link": "https://cdn-factory.marketjs.com/en/amazon-playable-ad/index.html",
        "img": "assets/img/games/game3.png",
        "video": "assets/video/games/game3.mp4",
        "is_recommended": false,
        "is_info": false
    }
]